README.rst
setup.py
ox_update/__init__.py
ox_update.egg-info/PKG-INFO
ox_update.egg-info/SOURCES.txt
ox_update.egg-info/dependency_links.txt
ox_update.egg-info/entry_points.txt
ox_update.egg-info/requires.txt
ox_update.egg-info/top_level.txt
ox_update/checking/__init__.py
ox_update/checking/common.py
ox_update/checking/noters.py
ox_update/checking/shell_checker.py
ox_update/ui/__init__.py
ox_update/ui/cmd_line.py