Metadata-Version: 1.1
Name: ox-update
Version: 0.2.0
Summary: Tools for updating software..
Home-page: http://github.com/emin63/ox_update
Author: Emin Martinian
Author-email: emin.martinian@gmail.com
License: MIT
Keywords: updating packages
Platform: UNKNOWN
Classifier: Development Status :: 3 - Alpha
Classifier: Intended Audience :: Developers
Classifier: Programming Language :: Python :: 3
